viettts/__init__.py
viettts/cli.py
viettts/flow/decoder.py
viettts/flow/flow.py
viettts/flow/flow_matching.py
viettts/flow/length_regulator.py
viettts/frontend.py
viettts/hifigan/f0_predictor.py
viettts/hifigan/generator.py
viettts/llm/llm.py
viettts/model.py
viettts/server.py
viettts/tokenizer/multilingual.tiktoken
viettts/tokenizer/tokenizer.py
viettts/transformer/__init__.py
viettts/transformer/activation.py
viettts/transformer/attention.py
viettts/transformer/convolution.py
viettts/transformer/decoder.py
viettts/transformer/decoder_layer.py
viettts/transformer/embedding.py
viettts/transformer/encoder.py
viettts/transformer/encoder_layer.py
viettts/transformer/label_smoothing_loss.py
viettts/transformer/positionwise_feed_forward.py
viettts/transformer/subsampling.py
viettts/transformer/transformer.py
viettts/tts.py
viettts/utils/__init__.py
viettts/utils/class_utils.py
viettts/utils/common.py
viettts/utils/file_utils.py
viettts/utils/frontend_utils.py
viettts/utils/mask.py
viettts/utils/vad.py
viet_tts-0.1.0.dist-info/LICENSE
viet_tts-0.1.0.dist-info/METADATA
viet_tts-0.1.0.dist-info/WHEEL
viet_tts-0.1.0.dist-info/entry_points.txt
viet_tts-0.1.0.dist-info/RECORD
