Metadata-Version: 2.1
Name: viet-tts
Version: 0.1.0
Summary: VietTTS: An Open-Source Vietnamese Text to Speech
Author: dangvansam
Author-email: dangvansam98@gmail.com
Requires-Python: >=3.10,<4.0
Classifier: Programming Language :: Python :: 3
Classifier: Programming Language :: Python :: 3.10
Classifier: Programming Language :: Python :: 3.11
Classifier: Programming Language :: Python :: 3.12
Requires-Dist: click (>=8.1.7,<9.0.0)
Requires-Dist: conformer (==0.3.2)
Requires-Dist: diffusers (==0.27.2)
Requires-Dist: fastapi (==0.111.0)
Requires-Dist: fastapi-cli (==0.0.4)
Requires-Dist: gradio (==4.32.2)
Requires-Dist: gunicorn (>=23.0.0,<24.0.0)
Requires-Dist: huggingface-hub (==0.24.7)
Requires-Dist: hydra-core (==1.3.2)
Requires-Dist: hyperpyyaml (==1.2.2)
Requires-Dist: librosa (==0.10.2)
Requires-Dist: loguru (==0.7.2)
Requires-Dist: omegaconf (==2.3.0)
Requires-Dist: onnx (==1.16.0)
Requires-Dist: onnxruntime-gpu (==1.16.0)
Requires-Dist: openai-whisper (>=20240930,<20240931)
Requires-Dist: protobuf (==4.25)
Requires-Dist: pydantic (==2.7.0)
Requires-Dist: silero-vad (>=5.1.2,<6.0.0)
Requires-Dist: soundfile (==0.12.1)
Requires-Dist: tiktoken (>=0.8.0,<0.9.0)
Requires-Dist: torch (==2.0.1)
Requires-Dist: torchaudio (==2.0.2)
Requires-Dist: uvicorn (==0.30.0)
Requires-Dist: vinorm (>=2.0.7,<3.0.0)
Requires-Dist: wget (==3.2)
